feed2fedi/__init__.py
feed2fedi/app.py
feed2fedi/collect.py
feed2fedi/control.py
feed2fedi/publish.py
feed2fedi/utils.py
feed2fedi-3.4.3.dist-info/WHEEL
feed2fedi-3.4.3.dist-info/entry_points.txt
feed2fedi-3.4.3.dist-info/METADATA
feed2fedi-3.4.3.dist-info/RECORD
