Metadata-Version: 2.3
Name: feed2fedi
Version: 3.4.3
Summary: Makes posts to Fediverse from one or more feeds
Author: marvin8
Author-email: marvin8 <marvin8@tuta.io>
License: AGPL-3.0-or-later
Classifier: Development Status :: 5 - Production/Stable
Classifier: Environment :: Console
Classifier: Programming Language :: Python
Classifier: Programming Language :: Python :: 3.10
Classifier: Programming Language :: Python :: 3.11
Classifier: Programming Language :: Python :: 3.12
Classifier: Programming Language :: Python :: 3.13
Requires-Dist: aiosqlite~=0.22.1
Requires-Dist: beautifulsoup4~=4.14.3
Requires-Dist: feedparser~=6.0.12
Requires-Dist: h11~=0.16.0
Requires-Dist: h2~=4.3.0
Requires-Dist: httpx~=0.28.1
Requires-Dist: icecream~=2.1.10
Requires-Dist: markdownify~=1.2.2
Requires-Dist: minimal-activitypub~=1.5.5
Requires-Dist: msgspec~=0.20.0
Requires-Dist: puremagic~=1.30
Requires-Dist: pycryptodomex~=3.23.0
Requires-Dist: stamina~=25.2.0
Requires-Dist: typer~=0.21.1
Requires-Dist: whenever~=0.9.5
Requires-Dist: yt-dlp~=2026.1.29
Requires-Python: >=3.10, <3.14
Project-URL: Changelog, https://codeberg.org/MarvinsMastodonTools/feed2fedi/src/branch/main/CHANGELOG.md
Project-URL: Issues, https://codeberg.org/MarvinsMastodonTools/feed2fedi/issues
Project-URL: Source, https://codeberg.org/MarvinsMastodonTools/feed2fedi
